{"time":["2024-07-27T10:16:35.000000000","2024-07-27T10:18:03.000000000","2024-07-27T10:18:24.000000000","2024-07-27T10:19:08.000000000","2024-07-27T10:19:12.000000000","2024-07-27T10:19:34.000000000","2024-07-27T10:19:41.000000000","2024-07-27T10:21:02.000000000","2024-07-27T10:21:21.000000000","2024-07-27T10:22:14.000000000","2024-07-27T10:25:12.000000000","2024-07-27T10:30:00.000000000","2024-07-27T10:32:01.000000000","2024-07-27T10:37:21.000000000","2024-07-27T10:37:22.000000000","2024-07-27T10:37:29.000000000","2024-07-27T10:37:32.000000000","2024-07-27T10:38:32.000000000","2024-07-27T10:38:35.000000000","2024-07-27T10:38:38.000000000","2024-07-27T10:41:20.000000000","2024-07-27T10:41:20.000000000","2024-07-27T10:41:21.000000000","2024-07-27T10:41:21.000000000","2024-07-27T10:41:28.000000000","2024-07-27T10:41:28.000000000","2024-07-27T10:41:28.000000000","2024-07-27T10:41:47.000000000","2024-07-27T10:48:49.000000000","2024-07-27T10:49:06.000000000","2024-07-27T10:50:00.000000000","2024-07-27T11:04:44.000000000","2024-07-27T11:26:49.000000000","2024-07-27T11:26:56.000000000","2024-07-27T11:28:00.000000000","2024-07-27T11:30:00.000000000","2024-07-27T11:30:24.000000000"],"cat":["Other","Other","Other","Other","Other","Other","Other","Other","Other","Other","Other","Flag","Drs","Flag","Flag","Flag","Flag","Flag","Flag","Flag","Flag","Flag","Flag","Flag","Flag","Flag","Flag","Other","Flag","Other","Flag","Flag","Flag","Other","Flag","Flag","Other"],"msg":["PINK HEAD PADDING MATERIAL MUST BE USED","DRS DISABLED IN ZONE 2","DRS ENABLED IN ZONE 2","WET TRACK","LOW GRIP CONDITIONS","DRS DISABLED IN ZONE 2","DRS ENABLED IN ZONE 2","DRS DISABLED IN ZONE 2","DRS ENABLED IN ZONE 2","DRS DISABLED IN ZONE 2","DRS ENABLED IN ZONE 2","GREEN LIGHT - PIT EXIT OPEN","DRS DISABLED","YELLOW IN TRACK SECTOR 8","CLEAR IN TRACK SECTOR 8","YELLOW IN TRACK SECTOR 8","CLEAR IN TRACK SECTOR 8","YELLOW IN TRACK SECTOR 8","DOUBLE YELLOW IN TRACK SECTOR 8","CLEAR IN TRACK SECTOR 8","YELLOW IN TRACK SECTOR 4","YELLOW IN TRACK SECTOR 5","DOUBLE YELLOW IN TRACK SECTOR 4","DOUBLE YELLOW IN TRACK SECTOR 5","RED FLAG","CLEAR IN TRACK SECTOR 4","CLEAR IN TRACK SECTOR 5","MEDICAL CAR DEPLOYED","TRACK CLEAR","SESSION WILL RESUME AT 12:50","GREEN LIGHT - PIT EXIT OPEN","RED FLAG","TRACK CLEAR","SESSION WILL RESUME AT 13:28","GREEN LIGHT - PIT EXIT OPEN","CHEQUERED FLAG","FIRST CAR TO TAKE THE FLAG - CAR 55 (SAI)"],"status":["None","None","None","None","None","None","None","None","None","None","None","None","DISABLED","None","None","None","None","None","None","None","None","None","None","None","None","None","None","None","None","None","None","None","None","None","None","None","None"],"flag":["None","None","None","None","None","None","None","None","None","None","None","GREEN","None","YELLOW","CLEAR","YELLOW","CLEAR","YELLOW","DOUBLE YELLOW","CLEAR","YELLOW","YELLOW","DOUBLE YELLOW","DOUBLE YELLOW","RED","CLEAR","CLEAR","None","CLEAR","None","GREEN","RED","CLEAR","None","GREEN","CHEQUERED","None"],"scope":["None","None","None","None","None","None","None","None","None","None","None","Track","None","Sector","Sector","Sector","Sector","Sector","Sector","Sector","Sector","Sector","Sector","Sector","Track","Sector","Sector","None","Track","None","Track","Track","Track","None","Track","Track","None"],"sector":["None","None","None","None","None","None","None","None","None","None","None","None","None",8.0,8.0,8.0,8.0,8.0,8.0,8.0,4.0,5.0,4.0,5.0,"None",4.0,5.0,"None","None","None","None","None","None","None","None","None","None"],"dNum":["None","None","None","None","None","None","None","None","None","None","None","None","None","None","None","None","None","None","None","None","None","None","None","None","None","None","None","None","None","None","None","None","None","None","None","None","None"],"lap":["None","None","None","None","None","None","None","None","None","None","None","None","None","None","None","None","None","None","None","None","None","None","None","None","None","None","None","None","None","None","None","None","None","None","None","None","None"]}